configstore/__init__.py
configstore/converters.py
configstore/store.py
configstore/backends/__init__.py
configstore/backends/awsssm.py
configstore/backends/dict.py
configstore/backends/docker_secret.py
configstore/backends/dotenv.py
configstore/backends/env_var.py
configstore-0.9.dist-info/LICENSE
configstore-0.9.dist-info/WHEEL
configstore-0.9.dist-info/METADATA
configstore-0.9.dist-info/RECORD
