Metadata-Version: 2.1
Name: configstore
Version: 0.9
Summary: Retrieve settings and secrets from different storages.
Author-email: Caravan Coop <hi@caravan.coop>
Requires-Python: >= 3
Classifier: Development Status :: 5 - Production/Stable
Classifier: Intended Audience :: Developers
Classifier: License :: OSI Approved :: MIT License
Classifier: Programming Language :: Python :: 3.10
Classifier: Programming Language :: Python :: 3.11
Classifier: Topic :: Software Development
Classifier: Topic :: System :: Installation/Setup
Classifier: Topic :: System :: Systems Administration
Requires-Dist: boto3 ; extra == "awsssm"
Requires-Dist: django-dotenv ; extra == "dotenv"
Requires-Dist: python-dotenv ; extra == "pydotenv"
Project-URL: Changelog, https://github.com/caravancoop/configstore/blob/main/CHANGELOG.rst
Project-URL: Documentation, https://github.com/caravancoop/configstore/blob/main/example.py
Project-URL: Homepage, https://github.com/caravancoop/configstore
Provides-Extra: awsssm
Provides-Extra: dotenv
Provides-Extra: pydotenv
